geofileops/__init__.py
geofileops/_compat.py
geofileops/fileops.py
geofileops/geoops.py
geofileops/py.typed
geofileops/version.txt
geofileops/helpers/__init__.py
geofileops/helpers/_configoptions_helper.py
geofileops/helpers/_general_helper.py
geofileops/helpers/_parameter_helper.py
geofileops/helpers/layerstyles.py
geofileops/util/__init__.py
geofileops/util/_general_util.py
geofileops/util/_geofileinfo.py
geofileops/util/_geometry_util.py
geofileops/util/_geoops_gpd.py
geofileops/util/_geoops_ogr.py
geofileops/util/_geoops_sql.py
geofileops/util/_geopath_util.py
geofileops/util/_geoseries_util.py
geofileops/util/_io_util.py
geofileops/util/_ogr_sql_util.py
geofileops/util/_ogr_util.py
geofileops/util/_processing_util.py
geofileops/util/_sqlite_userdefined.py
geofileops/util/_sqlite_util.py
geofileops/util/geodataframe_util.py
geofileops/util/geofiletypes.csv
geofileops/util/test.gpkg
geofileops-0.10.2.dist-info/licenses/LICENSE.txt
geofileops-0.10.2.dist-info/METADATA
geofileops-0.10.2.dist-info/WHEEL
geofileops-0.10.2.dist-info/top_level.txt
geofileops-0.10.2.dist-info/RECORD
