Metadata-Version: 2.4
Name: geofileops
Version: 0.10.2
Summary: Python toolbox to process large vector files faster.
Home-page: https://github.com/geofileops/geofileops
Author: Pieter Roggemans
Author-email: pieter.roggemans@gmail.com
Classifier: Intended Audience :: Science/Research
Classifier: License :: OSI Approved :: BSD License
Classifier: Operating System :: OS Independent
Classifier: Programming Language :: Python :: 3
Classifier: Programming Language :: Python :: 3 :: Only
Classifier: Topic :: Scientific/Engineering :: GIS
Requires-Python: >=3.10
License-File: LICENSE.txt
Requires-Dist: cloudpickle
Requires-Dist: gdal>=3.6
Requires-Dist: geopandas>=0.12
Requires-Dist: numpy
Requires-Dist: packaging
Requires-Dist: pandas>=1.5
Requires-Dist: psutil
Requires-Dist: pygeoops>=0.4
Requires-Dist: pyogrio>=0.7
Requires-Dist: pyproj
Requires-Dist: shapely>=2
Provides-Extra: full
Requires-Dist: simplification; extra == "full"
Dynamic: author
Dynamic: author-email
Dynamic: classifier
Dynamic: description
Dynamic: description-content-type
Dynamic: home-page
Dynamic: license-file
Dynamic: provides-extra
Dynamic: requires-dist
Dynamic: requires-python
Dynamic: summary
